ncsbe_lib/__init__.py
ncsbe_lib/collector.py
ncsbe_lib/ncsbe.py
ncsbe_lib/types.py
ncsbe_lib-1.3.1.dist-info/METADATA
ncsbe_lib-1.3.1.dist-info/WHEEL
ncsbe_lib-1.3.1.dist-info/RECORD
