Metadata-Version: 2.3
Name: ncsbe-lib
Version: 1.3.1
Summary: Python package for working with North Carolina State Board of Elections (NCSBE) historical election data
License: MIT
Author: Gregory Glasby
Author-email: trace.glasby@gmail.com
Requires-Python: >=3.9
Classifier: License :: OSI Approved :: MIT License
Classifier: Programming Language :: Python :: 3
Classifier: Programming Language :: Python :: 3.9
Classifier: Programming Language :: Python :: 3.10
Classifier: Programming Language :: Python :: 3.11
Classifier: Programming Language :: Python :: 3.12
Classifier: Programming Language :: Python :: 3.13
Requires-Dist: requests (>=2.26.0,<3.0.0)
